[
    {
        "Player": "Shohei Ohtani",
        "ID": "660271",
        "Year": 2024,
        "Team": "LAD",
        "Division": "National League West",
        "Type": "Batter",
        "PA": "731",
        "AB": "636",
        "H": "197",
        "2B": "38",
        "3B": "7",
        "HR": "54",
        "RBI": "130",
        "SO": "162",
        "BB": "81",
        "SB": "59",
        "CS": "4",
        "AVG": ".310",
        "OBP": ".390",
        "SLG": ".646",
        "OPS": "1.036",
        "Chase%": "26.6",
        "Whiff%": "29.8",
        "GB%": "36.3",
        "FB%": "31.3",
        "G/F": 1.16,
        "Sprint": 28.1,
        "AVG_Zone": [
            ".237",
            ".326",
            ".262",
            ".351",
            ".477",
            ".341",
            ".385",
            ".350",
            ".364",
            ".216",
            ".233",
            ".102",
            ".204"
        ]
    },
    {
        "Player": "Freddie Freeman",
        "ID": "518692",
        "Year": 2024,
        "Team": "LAD",
        "Division": "National League West",
        "Type": "Batter",
        "PA": "638",
        "AB": "542",
        "H": "153",
        "2B": "35",
        "3B": "2",
        "HR": "22",
        "RBI": "89",
        "SO": "100",
        "BB": "78",
        "SB": "9",
        "CS": "2",
        "AVG": ".282",
        "OBP": ".378",
        "SLG": ".476",
        "OPS": ".854",
        "Chase%": "26.6",
        "Whiff%": "20.2",
        "GB%": "38.7",
        "FB%": "31.1",
        "G/F": 1.24,
        "Sprint": 25.8,
        "AVG_Zone": [
            ".294",
            ".250",
            ".130",
            ".415",
            ".403",
            ".222",
            ".217",
            ".415",
            ".361",
            ".120",
            ".167",
            ".194",
            ".195"
        ]
    },
    {
        "Player": "Tommy Edman",
        "ID": "669242",
        "Year": 2024,
        "Team": "LAD",
        "Division": "National League West",
        "Type": "Batter",
        "PA": "153",
        "AB": "139",
        "H": "33",
        "2B": "5",
        "3B": "1",
        "HR": "6",
        "RBI": "20",
        "SO": "30",
        "BB": "11",
        "SB": "6",
        "CS": "0",
        "AVG": ".237",
        "OBP": ".294",
        "SLG": ".417",
        "OPS": ".711",
        "Chase%": "25.8",
        "Whiff%": "24.0",
        "GB%": "45.0",
        "FB%": "27.9",
        "G/F": 1.61,
        "Sprint": 27.9,
        "AVG_Zone": [
            ".250",
            ".333",
            ".000",
            ".353",
            ".417",
            ".000",
            ".143",
            ".333",
            ".286",
            ".000",
            ".200",
            ".000",
            ".125"
        ]
    },
    {
        "Player": "Chris Taylor",
        "ID": "621035",
        "Year": 2024,
        "Team": "LAD",
        "Division": "National League West",
        "Type": "Batter",
        "PA": "246",
        "AB": "213",
        "H": "43",
        "2B": "7",
        "3B": "1",
        "HR": "4",
        "RBI": "23",
        "SO": "76",
        "BB": "28",
        "SB": "5",
        "CS": "1",
        "AVG": ".202",
        "OBP": ".298",
        "SLG": ".300",
        "OPS": ".598",
        "Chase%": "19.6",
        "Whiff%": "31.3",
        "GB%": "42.1",
        "FB%": "25.0",
        "G/F": 1.68,
        "Sprint": 28.1,
        "AVG_Zone": [
            ".143",
            ".000",
            ".000",
            ".231",
            ".241",
            ".296",
            ".067",
            ".476",
            ".267",
            ".000",
            ".000",
            ".091",
            ".048"
        ]
    },
    {
        "Player": "Mookie Betts",
        "ID": "605141",
        "Year": 2024,
        "Team": "LAD",
        "Division": "National League West",
        "Type": "Batter",
        "PA": "516",
        "AB": "450",
        "H": "130",
        "2B": "24",
        "3B": "5",
        "HR": "19",
        "RBI": "75",
        "SO": "57",
        "BB": "61",
        "SB": "16",
        "CS": "2",
        "AVG": ".289",
        "OBP": ".372",
        "SLG": ".491",
        "OPS": ".863",
        "Chase%": "21.1",
        "Whiff%": "14.9",
        "GB%": "27.2",
        "FB%": "35.3",
        "G/F": 0.77,
        "Sprint": 26.7,
        "AVG_Zone": [
            ".318",
            ".158",
            ".414",
            ".472",
            ".250",
            ".340",
            ".294",
            ".297",
            ".283",
            ".222",
            ".235",
            ".300",
            ".207"
        ]
    },
    {
        "Player": "Teoscar Hernández",
        "ID": "606192",
        "Year": 2024,
        "Team": "LAD",
        "Division": "National League West",
        "Type": "Batter",
        "PA": "652",
        "AB": "589",
        "H": "160",
        "2B": "32",
        "3B": "2",
        "HR": "33",
        "RBI": "99",
        "SO": "188",
        "BB": "53",
        "SB": "12",
        "CS": "3",
        "AVG": ".272",
        "OBP": ".339",
        "SLG": ".501",
        "OPS": ".840",
        "Chase%": "28.7",
        "Whiff%": "34.0",
        "GB%": "46.5",
        "FB%": "26.6",
        "G/F": 1.75,
        "Sprint": 28.6,
        "AVG_Zone": [
            ".217",
            ".462",
            ".160",
            ".390",
            ".379",
            ".306",
            ".310",
            ".308",
            ".234",
            ".130",
            ".267",
            ".205",
            ".097"
        ]
    },
    {
        "Player": "Gavin Lux",
        "ID": "666158",
        "Year": 2024,
        "Team": "LAD",
        "Division": "National League West",
        "Type": "Batter",
        "PA": "487",
        "AB": "439",
        "H": "110",
        "2B": "24",
        "3B": "2",
        "HR": "10",
        "RBI": "50",
        "SO": "110",
        "BB": "44",
        "SB": "5",
        "CS": "2",
        "AVG": ".251",
        "OBP": ".320",
        "SLG": ".383",
        "OPS": ".703",
        "Chase%": "23.1",
        "Whiff%": "23.3",
        "GB%": "48.6",
        "FB%": "19.3",
        "G/F": 2.52,
        "Sprint": 27.7,
        "AVG_Zone": [
            ".235",
            ".250",
            ".185",
            ".241",
            ".344",
            ".368",
            ".290",
            ".273",
            ".359",
            ".273",
            ".133",
            ".077",
            ".000"
        ]
    },
    {
        "Player": "Will Smith",
        "ID": "669257",
        "Year": 2024,
        "Team": "LAD",
        "Division": "National League West",
        "Type": "Batter",
        "PA": "544",
        "AB": "476",
        "H": "118",
        "2B": "24",
        "3B": "2",
        "HR": "20",
        "RBI": "75",
        "SO": "105",
        "BB": "51",
        "SB": "1",
        "CS": "1",
        "AVG": ".248",
        "OBP": ".327",
        "SLG": ".433",
        "OPS": ".760",
        "Chase%": "26.3",
        "Whiff%": "20.9",
        "GB%": "33.0",
        "FB%": "40.4",
        "G/F": 0.82,
        "Sprint": 27.4,
        "AVG_Zone": [
            ".320",
            ".237",
            ".308",
            ".394",
            ".258",
            ".254",
            ".136",
            ".314",
            ".179",
            ".400",
            ".207",
            ".130",
            ".111"
        ]
    },
    {
        "Player": "Miguel Rojas",
        "ID": "500743",
        "Year": 2024,
        "Team": "LAD",
        "Division": "National League West",
        "Type": "Batter",
        "PA": "337",
        "AB": "307",
        "H": "87",
        "2B": "21",
        "3B": "0",
        "HR": "6",
        "RBI": "36",
        "SO": "34",
        "BB": "23",
        "SB": "8",
        "CS": "2",
        "AVG": ".283",
        "OBP": ".337",
        "SLG": ".410",
        "OPS": ".747",
        "Chase%": "27.3",
        "Whiff%": "13.9",
        "GB%": "49.5",
        "FB%": "17.3",
        "G/F": 2.86,
        "Sprint": 25.8,
        "AVG_Zone": [
            ".308",
            ".310",
            ".250",
            ".382",
            ".350",
            ".207",
            ".267",
            ".343",
            ".237",
            ".222",
            ".167",
            ".273",
            ".200"
        ]
    },
    {
        "Player": "James Outman",
        "ID": "681546",
        "Year": 2024,
        "Team": "LAD",
        "Division": "National League West",
        "Type": "Batter",
        "PA": "156",
        "AB": "136",
        "H": "20",
        "2B": "4",
        "3B": "0",
        "HR": "4",
        "RBI": "11",
        "SO": "55",
        "BB": "16",
        "SB": "2",
        "CS": "1",
        "AVG": ".147",
        "OBP": ".256",
        "SLG": ".265",
        "OPS": ".521",
        "Chase%": "28.2",
        "Whiff%": "37.1",
        "GB%": "33.3",
        "FB%": "28.4",
        "G/F": 1.17,
        "Sprint": 28.8,
        "AVG_Zone": [
            ".000",
            ".154",
            ".000",
            ".250",
            ".250",
            ".063",
            ".400",
            ".231",
            ".000",
            ".333",
            ".000",
            ".048",
            ".000"
        ]
    },
    {
        "Player": "Enrique Hernández",
        "ID": "571771",
        "Year": 2024,
        "Team": "LAD",
        "Division": "National League West",
        "Type": "Batter",
        "PA": "393",
        "AB": "362",
        "H": "83",
        "2B": "16",
        "3B": "0",
        "HR": "12",
        "RBI": "42",
        "SO": "77",
        "BB": "27",
        "SB": "0",
        "CS": "0",
        "AVG": ".229",
        "OBP": ".281",
        "SLG": ".373",
        "OPS": ".654",
        "Chase%": "26.4",
        "Whiff%": "22.9",
        "GB%": "35.6",
        "FB%": "29.4",
        "G/F": 1.21,
        "Sprint": 27.0,
        "AVG_Zone": [
            ".222",
            ".065",
            ".000",
            ".395",
            ".200",
            ".344",
            ".278",
            ".333",
            ".186",
            ".273",
            ".333",
            ".280",
            ".095"
        ]
    },
    {
        "Player": "Hunter Feduccia",
        "ID": "676439",
        "Year": 2024,
        "Team": "LAD",
        "Division": "National League West",
        "Type": "Batter",
        "PA": "14",
        "AB": "12",
        "H": "4",
        "2B": "0",
        "3B": "0",
        "HR": "0",
        "RBI": "1",
        "SO": "2",
        "BB": "2",
        "SB": "0",
        "CS": "0",
        "AVG": ".333",
        "OBP": ".429",
        "SLG": ".333",
        "OPS": ".762",
        "Chase%": "7.7",
        "Whiff%": "19.2",
        "GB%": "60.0",
        "FB%": "20.0",
        "G/F": 3.0,
        "Sprint": 27.6,
        "AVG_Zone": [
            "1.000",
            ".500",
            ".000",
            "1.000",
            ".000",
            ".500",
            ".000",
            ".000",
            ".000",
            ".000",
            ".000",
            ".000",
            ".000"
        ]
    },
    {
        "Player": "Andy Pages",
        "ID": "681624",
        "Year": 2024,
        "Team": "LAD",
        "Division": "National League West",
        "Type": "Batter",
        "PA": "443",
        "AB": "403",
        "H": "100",
        "2B": "23",
        "3B": "1",
        "HR": "13",
        "RBI": "46",
        "SO": "108",
        "BB": "29",
        "SB": "1",
        "CS": "2",
        "AVG": ".248",
        "OBP": ".305",
        "SLG": ".407",
        "OPS": ".712",
        "Chase%": "30.7",
        "Whiff%": "26.1",
        "GB%": "32.8",
        "FB%": "30.4",
        "G/F": 1.08,
        "Sprint": 28.3,
        "AVG_Zone": [
            ".000",
            ".190",
            ".273",
            ".349",
            ".357",
            ".195",
            ".500",
            ".386",
            ".189",
            ".063",
            ".000",
            ".194",
            ".158"
        ]
    },
    {
        "Player": "Max Muncy",
        "ID": "571970",
        "Year": 2024,
        "Team": "LAD",
        "Division": "National League West",
        "Type": "Batter",
        "PA": "293",
        "AB": "237",
        "H": "55",
        "2B": "17",
        "3B": "0",
        "HR": "15",
        "RBI": "48",
        "SO": "77",
        "BB": "45",
        "SB": "1",
        "CS": "0",
        "AVG": ".232",
        "OBP": ".358",
        "SLG": ".494",
        "OPS": ".852",
        "Chase%": "20.3",
        "Whiff%": "31.0",
        "GB%": "25.3",
        "FB%": "43.4",
        "G/F": 0.58,
        "Sprint": 26.9,
        "AVG_Zone": [
            ".083",
            ".269",
            ".182",
            ".333",
            ".333",
            ".571",
            ".207",
            ".235",
            ".000",
            ".154",
            ".000",
            ".194",
            ".000"
        ]
    },
    {
        "Player": "Austin Barnes",
        "ID": "605131",
        "Year": 2024,
        "Team": "LAD",
        "Division": "National League West",
        "Type": "Batter",
        "PA": "156",
        "AB": "140",
        "H": "37",
        "2B": "3",
        "3B": "0",
        "HR": "1",
        "RBI": "11",
        "SO": "36",
        "BB": "14",
        "SB": "3",
        "CS": "0",
        "AVG": ".264",
        "OBP": ".331",
        "SLG": ".307",
        "OPS": ".638",
        "Chase%": "19.6",
        "Whiff%": "22.8",
        "GB%": "50.0",
        "FB%": "16.0",
        "G/F": 3.12,
        "Sprint": 25.8,
        "AVG_Zone": [
            ".286",
            ".333",
            ".167",
            ".400",
            ".348",
            ".200",
            ".000",
            ".417",
            ".211",
            ".500",
            ".000",
            ".000",
            ".250"
        ]
    },
    {
        "Player": "Kevin Kiermaier",
        "ID": "595281",
        "Year": 2024,
        "Team": "TOR",
        "Division": "National League West",
        "Type": "Batter",
        "PA": "217",
        "AB": "200",
        "H": "39",
        "2B": "7",
        "3B": "2",
        "HR": "4",
        "RBI": "18",
        "SO": "66",
        "BB": "10",
        "SB": "5",
        "CS": "0",
        "AVG": ".195",
        "OBP": ".236",
        "SLG": ".310",
        "OPS": ".546",
        "Chase%": "33.1",
        "Whiff%": "37.5",
        "GB%": "55.8",
        "FB%": "18.8",
        "G/F": 2.97,
        "Sprint": 28.7,
        "AVG_Zone": [
            ".071",
            ".214",
            ".500",
            ".238",
            ".244",
            ".214",
            ".333",
            ".154",
            ".235",
            ".000",
            ".000",
            ".222",
            ".111"
        ]
    },
    {
        "Player": "Kevin Kiermaier",
        "ID": "595281",
        "Year": 2024,
        "Team": "LAD",
        "Division": "National League West",
        "Type": "Batter",
        "PA": "64",
        "AB": "59",
        "H": "12",
        "2B": "2",
        "3B": "1",
        "HR": "1",
        "RBI": "8",
        "SO": "20",
        "BB": "2",
        "SB": "1",
        "CS": "2",
        "AVG": ".203",
        "OBP": ".242",
        "SLG": ".322",
        "OPS": ".564",
        "Chase%": "33.1",
        "Whiff%": "37.5",
        "GB%": "55.8",
        "FB%": "18.8",
        "G/F": 2.97,
        "Sprint": 28.7,
        "AVG_Zone": [
            ".071",
            ".214",
            ".500",
            ".238",
            ".244",
            ".214",
            ".333",
            ".154",
            ".235",
            ".000",
            ".000",
            ".222",
            ".111"
        ]
    },
    {
        "Player": "Kevin Kiermaier",
        "ID": "595281",
        "Year": 2024,
        "Team": "2 Teams",
        "Division": "National League West",
        "Type": "Batter",
        "PA": "281",
        "AB": "259",
        "H": "51",
        "2B": "9",
        "3B": "3",
        "HR": "5",
        "RBI": "26",
        "SO": "86",
        "BB": "12",
        "SB": "6",
        "CS": "2",
        "AVG": ".197",
        "OBP": ".237",
        "SLG": ".313",
        "OPS": ".550",
        "Chase%": "33.1",
        "Whiff%": "37.5",
        "GB%": "55.8",
        "FB%": "18.8",
        "G/F": 2.97,
        "Sprint": 28.7,
        "AVG_Zone": [
            ".071",
            ".214",
            ".500",
            ".238",
            ".244",
            ".214",
            ".333",
            ".154",
            ".235",
            ".000",
            ".000",
            ".222",
            ".111"
        ]
    },
    {
        "Player": "Zach Logue",
        "ID": "656657",
        "Year": 2024,
        "Team": "LAD",
        "Division": "National League West",
        "Type": "Pitcher",
        "Wins": "0",
        "Losses": "0",
        "ERA": "18.00",
        "IP": "2.0",
        "Hits": "6",
        "Runs": "4",
        "ER": "4",
        "HR": "1",
        "BB": "0",
        "SO": "4",
        "WHIP": "3.00",
        "Chase%": "52.6",
        "Whiff%": "34.6",
        "GB%": "50.0",
        "FB%": "12.5",
        "G/F": 4.0,
        "Pitch_Zone%": [
            "3",
            "3",
            "3",
            "5",
            "2",
            "4",
            "1",
            "1",
            "2",
            "6",
            "6",
            "7",
            "0"
        ]
    },
    {
        "Player": "Justin Wrobleski",
        "ID": "680736",
        "Year": 2024,
        "Team": "LAD",
        "Division": "National League West",
        "Type": "Pitcher",
        "Wins": "1",
        "Losses": "2",
        "ERA": "5.70",
        "IP": "36.1",
        "Hits": "34",
        "Runs": "24",
        "ER": "23",
        "HR": "9",
        "BB": "16",
        "SO": "26",
        "WHIP": "1.38",
        "Chase%": "24.5",
        "Whiff%": "22.3",
        "GB%": "31.5",
        "FB%": "29.7",
        "G/F": 1.06,
        "Pitch_Zone%": [
            "36",
            "42",
            "28",
            "44",
            "55",
            "32",
            "24",
            "34",
            "11",
            "50",
            "101",
            "112",
            "23"
        ]
    },
    {
        "Player": "Walker Buehler",
        "ID": "621111",
        "Year": 2024,
        "Team": "LAD",
        "Division": "National League West",
        "Type": "Pitcher",
        "Wins": "1",
        "Losses": "6",
        "ERA": "5.38",
        "IP": "75.1",
        "Hits": "89",
        "Runs": "52",
        "ER": "45",
        "HR": "16",
        "BB": "28",
        "SO": "64",
        "WHIP": "1.55",
        "Chase%": "24.5",
        "Whiff%": "19.4",
        "GB%": "45.9",
        "FB%": "22.4",
        "G/F": 2.05,
        "Pitch_Zone%": [
            "66",
            "60",
            "65",
            "71",
            "96",
            "104",
            "52",
            "73",
            "93",
            "142",
            "111",
            "99",
            "304"
        ]
    },
    {
        "Player": "Brusdar Graterol",
        "ID": "660813",
        "Year": 2024,
        "Team": "LAD",
        "Division": "National League West",
        "Type": "Pitcher",
        "Wins": "0",
        "Losses": "0",
        "ERA": "2.45",
        "IP": "7.1",
        "Hits": "3",
        "Runs": "2",
        "ER": "2",
        "HR": "0",
        "BB": "2",
        "SO": "7",
        "WHIP": "0.68",
        "Chase%": "34.6",
        "Whiff%": "26.5",
        "GB%": "44.4",
        "FB%": "11.1",
        "G/F": 4.0,
        "Pitch_Zone%": [
            "5",
            "3",
            "4",
            "7",
            "8",
            "10",
            "2",
            "6",
            "4",
            "7",
            "9",
            "4",
            "32"
        ]
    },
    {
        "Player": "Ben Casparius",
        "ID": "676508",
        "Year": 2024,
        "Team": "LAD",
        "Division": "National League West",
        "Type": "Pitcher",
        "Wins": "2",
        "Losses": "0",
        "ERA": "2.16",
        "IP": "8.1",
        "Hits": "9",
        "Runs": "3",
        "ER": "2",
        "HR": "0",
        "BB": "4",
        "SO": "12",
        "WHIP": "1.56",
        "Chase%": "25.8",
        "Whiff%": "34.7",
        "GB%": "23.8",
        "FB%": "38.1",
        "G/F": 0.62,
        "Pitch_Zone%": [
            "14",
            "11",
            "11",
            "7",
            "8",
            "11",
            "6",
            "8",
            "14",
            "20",
            "18",
            "8",
            "20"
        ]
    },
    {
        "Player": "Ryan Brasier",
        "ID": "518489",
        "Year": 2024,
        "Team": "LAD",
        "Division": "National League West",
        "Type": "Pitcher",
        "Wins": "1",
        "Losses": "0",
        "ERA": "3.54",
        "IP": "28.0",
        "Hits": "22",
        "Runs": "12",
        "ER": "11",
        "HR": "3",
        "BB": "5",
        "SO": "25",
        "WHIP": "0.96",
        "Chase%": "34.8",
        "Whiff%": "22.3",
        "GB%": "45.0",
        "FB%": "22.5",
        "G/F": 2.0,
        "Pitch_Zone%": [
            "17",
            "18",
            "18",
            "20",
            "32",
            "21",
            "15",
            "37",
            "32",
            "30",
            "15",
            "23",
            "96"
        ]
    },
    {
        "Player": "River Ryan",
        "ID": "689981",
        "Year": 2024,
        "Team": "LAD",
        "Division": "National League West",
        "Type": "Pitcher",
        "Wins": "1",
        "Losses": "0",
        "ERA": "1.33",
        "IP": "20.1",
        "Hits": "15",
        "Runs": "4",
        "ER": "3",
        "HR": "1",
        "BB": "9",
        "SO": "18",
        "WHIP": "1.18",
        "Chase%": "23.8",
        "Whiff%": "23.9",
        "GB%": "50.0",
        "FB%": "25.9",
        "G/F": 1.93,
        "Pitch_Zone%": [
            "4",
            "14",
            "10",
            "14",
            "28",
            "20",
            "14",
            "14",
            "26",
            "37",
            "23",
            "25",
            "66"
        ]
    },
    {
        "Player": "Clayton Kershaw",
        "ID": "477132",
        "Year": 2024,
        "Team": "LAD",
        "Division": "National League West",
        "Type": "Pitcher",
        "Wins": "2",
        "Losses": "2",
        "ERA": "4.50",
        "IP": "30.0",
        "Hits": "36",
        "Runs": "19",
        "ER": "15",
        "HR": "2",
        "BB": "9",
        "SO": "24",
        "WHIP": "1.50",
        "Chase%": "26.5",
        "Whiff%": "21.7",
        "GB%": "39.8",
        "FB%": "19.4",
        "G/F": 2.05,
        "Pitch_Zone%": [
            "22",
            "30",
            "21",
            "32",
            "43",
            "26",
            "48",
            "38",
            "18",
            "25",
            "51",
            "106",
            "44"
        ]
    },
    {
        "Player": "Michael Grove",
        "ID": "675627",
        "Year": 2024,
        "Team": "LAD",
        "Division": "National League West",
        "Type": "Pitcher",
        "Wins": "4",
        "Losses": "4",
        "ERA": "5.12",
        "IP": "51.0",
        "Hits": "46",
        "Runs": "31",
        "ER": "29",
        "HR": "6",
        "BB": "16",
        "SO": "54",
        "WHIP": "1.22",
        "Chase%": "28.6",
        "Whiff%": "26.6",
        "GB%": "45.3",
        "FB%": "22.3",
        "G/F": 2.03,
        "Pitch_Zone%": [
            "34",
            "34",
            "32",
            "26",
            "65",
            "67",
            "18",
            "47",
            "92",
            "38",
            "41",
            "35",
            "298"
        ]
    },
    {
        "Player": "Anthony Banda",
        "ID": "607455",
        "Year": 2024,
        "Team": "LAD",
        "Division": "National League West",
        "Type": "Pitcher",
        "Wins": "3",
        "Losses": "2",
        "ERA": "3.08",
        "IP": "49.2",
        "Hits": "44",
        "Runs": "19",
        "ER": "17",
        "HR": "5",
        "BB": "18",
        "SO": "50",
        "WHIP": "1.25",
        "Chase%": "31.4",
        "Whiff%": "30.0",
        "GB%": "46.0",
        "FB%": "23.7",
        "G/F": 1.94,
        "Pitch_Zone%": [
            "37",
            "39",
            "44",
            "44",
            "53",
            "56",
            "44",
            "41",
            "37",
            "37",
            "130",
            "152",
            "60"
        ]
    },
    {
        "Player": "Blake Treinen",
        "ID": "595014",
        "Year": 2024,
        "Team": "LAD",
        "Division": "National League West",
        "Type": "Pitcher",
        "Wins": "7",
        "Losses": "3",
        "ERA": "1.93",
        "IP": "46.2",
        "Hits": "33",
        "Runs": "11",
        "ER": "10",
        "HR": "5",
        "BB": "11",
        "SO": "56",
        "WHIP": "0.94",
        "Chase%": "35.2",
        "Whiff%": "27.9",
        "GB%": "44.3",
        "FB%": "31.3",
        "G/F": 1.42,
        "Pitch_Zone%": [
            "43",
            "35",
            "28",
            "32",
            "56",
            "50",
            "28",
            "49",
            "44",
            "106",
            "44",
            "48",
            "174"
        ]
    },
    {
        "Player": "Yoshinobu Yamamoto",
        "ID": "808967",
        "Year": 2024,
        "Team": "LAD",
        "Division": "National League West",
        "Type": "Pitcher",
        "Wins": "7",
        "Losses": "2",
        "ERA": "3.00",
        "IP": "90.0",
        "Hits": "78",
        "Runs": "32",
        "ER": "30",
        "HR": "7",
        "BB": "22",
        "SO": "105",
        "WHIP": "1.11",
        "Chase%": "31.7",
        "Whiff%": "27.0",
        "GB%": "48.3",
        "FB%": "20.0",
        "G/F": 2.42,
        "Pitch_Zone%": [
            "57",
            "47",
            "40",
            "107",
            "109",
            "87",
            "107",
            "110",
            "86",
            "148",
            "56",
            "229",
            "286"
        ]
    },
    {
        "Player": "Kyle Hurt",
        "ID": "669165",
        "Year": 2024,
        "Team": "LAD",
        "Division": "National League West",
        "Type": "Pitcher",
        "Wins": "0",
        "Losses": "1",
        "ERA": "1.35",
        "IP": "6.2",
        "Hits": "8",
        "Runs": "2",
        "ER": "1",
        "HR": "0",
        "BB": "1",
        "SO": "3",
        "WHIP": "1.35",
        "Chase%": "37.8",
        "Whiff%": "25.5",
        "GB%": "34.8",
        "FB%": "17.4",
        "G/F": 2.0,
        "Pitch_Zone%": [
            "5",
            "7",
            "0",
            "8",
            "13",
            "5",
            "4",
            "8",
            "0",
            "15",
            "2",
            "3",
            "17"
        ]
    },
    {
        "Player": "Evan Phillips",
        "ID": "623465",
        "Year": 2024,
        "Team": "LAD",
        "Division": "National League West",
        "Type": "Pitcher",
        "Wins": "5",
        "Losses": "1",
        "ERA": "3.62",
        "IP": "54.2",
        "Hits": "48",
        "Runs": "30",
        "ER": "22",
        "HR": "6",
        "BB": "17",
        "SO": "63",
        "WHIP": "1.19",
        "Chase%": "27.9",
        "Whiff%": "27.7",
        "GB%": "40.1",
        "FB%": "32.7",
        "G/F": 1.23,
        "Pitch_Zone%": [
            "42",
            "50",
            "41",
            "52",
            "74",
            "75",
            "29",
            "61",
            "55",
            "105",
            "52",
            "59",
            "222"
        ]
    },
    {
        "Player": "Joe Kelly",
        "ID": "523260",
        "Year": 2024,
        "Team": "LAD",
        "Division": "National League West",
        "Type": "Pitcher",
        "Wins": "1",
        "Losses": "1",
        "ERA": "4.78",
        "IP": "32.0",
        "Hits": "31",
        "Runs": "19",
        "ER": "17",
        "HR": "4",
        "BB": "16",
        "SO": "35",
        "WHIP": "1.47",
        "Chase%": "23.7",
        "Whiff%": "22.4",
        "GB%": "47.7",
        "FB%": "23.3",
        "G/F": 2.05,
        "Pitch_Zone%": [
            "25",
            "20",
            "11",
            "37",
            "52",
            "30",
            "30",
            "29",
            "44",
            "73",
            "22",
            "53",
            "126"
        ]
    },
    {
        "Player": "Bobby Miller",
        "ID": "676272",
        "Year": 2024,
        "Team": "LAD",
        "Division": "National League West",
        "Type": "Pitcher",
        "Wins": "2",
        "Losses": "4",
        "ERA": "8.52",
        "IP": "56.0",
        "Hits": "69",
        "Runs": "53",
        "ER": "53",
        "HR": "17",
        "BB": "30",
        "SO": "52",
        "WHIP": "1.77",
        "Chase%": "24.2",
        "Whiff%": "23.7",
        "GB%": "44.8",
        "FB%": "25.3",
        "G/F": 1.77,
        "Pitch_Zone%": [
            "41",
            "51",
            "25",
            "57",
            "81",
            "47",
            "51",
            "84",
            "59",
            "115",
            "55",
            "111",
            "276"
        ]
    },
    {
        "Player": "Edgardo Henriquez",
        "ID": "683618",
        "Year": 2024,
        "Team": "LAD",
        "Division": "National League West",
        "Type": "Pitcher",
        "Wins": "0",
        "Losses": "0",
        "ERA": "2.70",
        "IP": "3.1",
        "Hits": "2",
        "Runs": "1",
        "ER": "1",
        "HR": "0",
        "BB": "2",
        "SO": "5",
        "WHIP": "1.20",
        "Chase%": "32.3",
        "Whiff%": "25.9",
        "GB%": "42.9",
        "FB%": "0.0",
        "G/F": 10000,
        "Pitch_Zone%": [
            "4",
            "1",
            "0",
            "5",
            "1",
            "2",
            "5",
            "4",
            "6",
            "10",
            "3",
            "6",
            "12"
        ]
    },
    {
        "Player": "Brent Honeywell",
        "ID": "641703",
        "Year": 2024,
        "Team": "PIT",
        "Division": "National League West",
        "Type": "Pitcher",
        "Wins": "0",
        "Losses": "0",
        "ERA": "2.70",
        "IP": "3.1",
        "Hits": "3",
        "Runs": "1",
        "ER": "1",
        "HR": "0",
        "BB": "2",
        "SO": "1",
        "WHIP": "1.50",
        "Chase%": "22.3",
        "Whiff%": "15.3",
        "GB%": "43.2",
        "FB%": "31.4",
        "G/F": 1.38,
        "Pitch_Zone%": [
            "13",
            "10",
            "15",
            "17",
            "21",
            "22",
            "13",
            "25",
            "20",
            "18",
            "11",
            "17",
            "70"
        ]
    },
    {
        "Player": "Brent Honeywell",
        "ID": "641703",
        "Year": 2024,
        "Team": "LAD",
        "Division": "National League West",
        "Type": "Pitcher",
        "Wins": "1",
        "Losses": "1",
        "ERA": "2.62",
        "IP": "34.1",
        "Hits": "29",
        "Runs": "11",
        "ER": "10",
        "HR": "3",
        "BB": "9",
        "SO": "17",
        "WHIP": "1.11",
        "Chase%": "22.3",
        "Whiff%": "15.3",
        "GB%": "43.2",
        "FB%": "31.4",
        "G/F": 1.38,
        "Pitch_Zone%": [
            "13",
            "10",
            "15",
            "17",
            "21",
            "22",
            "13",
            "25",
            "20",
            "18",
            "11",
            "17",
            "70"
        ]
    },
    {
        "Player": "Brent Honeywell",
        "ID": "641703",
        "Year": 2024,
        "Team": "2 Teams",
        "Division": "National League West",
        "Type": "Pitcher",
        "Wins": "1",
        "Losses": "1",
        "ERA": "2.63",
        "IP": "37.2",
        "Hits": "32",
        "Runs": "12",
        "ER": "11",
        "HR": "3",
        "BB": "11",
        "SO": "18",
        "WHIP": "1.14",
        "Chase%": "22.3",
        "Whiff%": "15.3",
        "GB%": "43.2",
        "FB%": "31.4",
        "G/F": 1.38,
        "Pitch_Zone%": [
            "13",
            "10",
            "15",
            "17",
            "21",
            "22",
            "13",
            "25",
            "20",
            "18",
            "11",
            "17",
            "70"
        ]
    },
    {
        "Player": "Jack Flaherty",
        "ID": "656427",
        "Year": 2024,
        "Team": "DET",
        "Division": "National League West",
        "Type": "Pitcher",
        "Wins": "7",
        "Losses": "5",
        "ERA": "2.95",
        "IP": "106.2",
        "Hits": "83",
        "Runs": "38",
        "ER": "35",
        "HR": "15",
        "BB": "19",
        "SO": "133",
        "WHIP": "0.96",
        "Chase%": "30.7",
        "Whiff%": "32.1",
        "GB%": "40.2",
        "FB%": "26.9",
        "G/F": 1.49,
        "Pitch_Zone%": [
            "38",
            "49",
            "22",
            "61",
            "90",
            "80",
            "48",
            "96",
            "82",
            "55",
            "20",
            "119",
            "418"
        ]
    },
    {
        "Player": "Jack Flaherty",
        "ID": "656427",
        "Year": 2024,
        "Team": "LAD",
        "Division": "National League West",
        "Type": "Pitcher",
        "Wins": "6",
        "Losses": "2",
        "ERA": "3.58",
        "IP": "55.1",
        "Hits": "52",
        "Runs": "23",
        "ER": "22",
        "HR": "9",
        "BB": "19",
        "SO": "61",
        "WHIP": "1.28",
        "Chase%": "30.7",
        "Whiff%": "32.1",
        "GB%": "40.2",
        "FB%": "26.9",
        "G/F": 1.49,
        "Pitch_Zone%": [
            "38",
            "49",
            "22",
            "61",
            "90",
            "80",
            "48",
            "96",
            "82",
            "55",
            "20",
            "119",
            "418"
        ]
    },
    {
        "Player": "Jack Flaherty",
        "ID": "656427",
        "Year": 2024,
        "Team": "2 Teams",
        "Division": "National League West",
        "Type": "Pitcher",
        "Wins": "13",
        "Losses": "7",
        "ERA": "3.17",
        "IP": "162.0",
        "Hits": "135",
        "Runs": "61",
        "ER": "57",
        "HR": "24",
        "BB": "38",
        "SO": "194",
        "WHIP": "1.07",
        "Chase%": "30.7",
        "Whiff%": "32.1",
        "GB%": "40.2",
        "FB%": "26.9",
        "G/F": 1.49,
        "Pitch_Zone%": [
            "38",
            "49",
            "22",
            "61",
            "90",
            "80",
            "48",
            "96",
            "82",
            "55",
            "20",
            "119",
            "418"
        ]
    },
    {
        "Player": "Alex Vesia",
        "ID": "681911",
        "Year": 2024,
        "Team": "LAD",
        "Division": "National League West",
        "Type": "Pitcher",
        "Wins": "5",
        "Losses": "4",
        "ERA": "1.76",
        "IP": "66.1",
        "Hits": "33",
        "Runs": "19",
        "ER": "13",
        "HR": "7",
        "BB": "33",
        "SO": "87",
        "WHIP": "0.99",
        "Chase%": "26.6",
        "Whiff%": "31.3",
        "GB%": "25.7",
        "FB%": "37.9",
        "G/F": 0.68,
        "Pitch_Zone%": [
            "54",
            "87",
            "72",
            "52",
            "73",
            "70",
            "50",
            "48",
            "28",
            "126",
            "198",
            "192",
            "59"
        ]
    },
    {
        "Player": "Landon Knack",
        "ID": "689017",
        "Year": 2024,
        "Team": "LAD",
        "Division": "National League West",
        "Type": "Pitcher",
        "Wins": "3",
        "Losses": "5",
        "ERA": "3.65",
        "IP": "69.0",
        "Hits": "58",
        "Runs": "28",
        "ER": "28",
        "HR": "14",
        "BB": "18",
        "SO": "69",
        "WHIP": "1.10",
        "Chase%": "25.7",
        "Whiff%": "23.1",
        "GB%": "31.1",
        "FB%": "36.7",
        "G/F": 0.85,
        "Pitch_Zone%": [
            "62",
            "81",
            "43",
            "56",
            "96",
            "74",
            "41",
            "54",
            "59",
            "204",
            "71",
            "57",
            "251"
        ]
    },
    {
        "Player": "Connor Brogdon",
        "ID": "641401",
        "Year": 2024,
        "Team": "PHI",
        "Division": "National League West",
        "Type": "Pitcher",
        "Wins": "0",
        "Losses": "1",
        "ERA": "27.00",
        "IP": "2.0",
        "Hits": "3",
        "Runs": "7",
        "ER": "6",
        "HR": "2",
        "BB": "6",
        "SO": "3",
        "WHIP": "4.50",
        "Chase%": "14.8",
        "Whiff%": "28.2",
        "GB%": "30.0",
        "FB%": "60.0",
        "G/F": 0.5,
        "Pitch_Zone%": [
            "0",
            "6",
            "0",
            "5",
            "4",
            "6",
            "6",
            "8",
            "8",
            "12",
            "7",
            "3",
            "32"
        ]
    },
    {
        "Player": "Connor Brogdon",
        "ID": "641401",
        "Year": 2024,
        "Team": "LAD",
        "Division": "National League West",
        "Type": "Pitcher",
        "Wins": "0",
        "Losses": "0",
        "ERA": "18.00",
        "IP": "1.0",
        "Hits": "2",
        "Runs": "2",
        "ER": "2",
        "HR": "2",
        "BB": "0",
        "SO": "0",
        "WHIP": "2.00",
        "Chase%": "14.8",
        "Whiff%": "28.2",
        "GB%": "30.0",
        "FB%": "60.0",
        "G/F": 0.5,
        "Pitch_Zone%": [
            "0",
            "6",
            "0",
            "5",
            "4",
            "6",
            "6",
            "8",
            "8",
            "12",
            "7",
            "3",
            "32"
        ]
    },
    {
        "Player": "Connor Brogdon",
        "ID": "641401",
        "Year": 2024,
        "Team": "2 Teams",
        "Division": "National League West",
        "Type": "Pitcher",
        "Wins": "0",
        "Losses": "1",
        "ERA": "24.00",
        "IP": "3.0",
        "Hits": "5",
        "Runs": "9",
        "ER": "8",
        "HR": "4",
        "BB": "6",
        "SO": "3",
        "WHIP": "3.67",
        "Chase%": "14.8",
        "Whiff%": "28.2",
        "GB%": "30.0",
        "FB%": "60.0",
        "G/F": 0.5,
        "Pitch_Zone%": [
            "0",
            "6",
            "0",
            "5",
            "4",
            "6",
            "6",
            "8",
            "8",
            "12",
            "7",
            "3",
            "32"
        ]
    },
    {
        "Player": "Daniel Hudson",
        "ID": "543339",
        "Year": 2024,
        "Team": "LAD",
        "Division": "National League West",
        "Type": "Pitcher",
        "Wins": "6",
        "Losses": "2",
        "ERA": "3.00",
        "IP": "63.0",
        "Hits": "46",
        "Runs": "25",
        "ER": "21",
        "HR": "10",
        "BB": "19",
        "SO": "63",
        "WHIP": "1.03",
        "Chase%": "24.9",
        "Whiff%": "32.3",
        "GB%": "38.8",
        "FB%": "35.3",
        "G/F": 1.1,
        "Pitch_Zone%": [
            "55",
            "61",
            "32",
            "68",
            "65",
            "52",
            "32",
            "52",
            "71",
            "132",
            "42",
            "61",
            "276"
        ]
    },
    {
        "Player": "Gavin Stone",
        "ID": "694813",
        "Year": 2024,
        "Team": "LAD",
        "Division": "National League West",
        "Type": "Pitcher",
        "Wins": "11",
        "Losses": "5",
        "ERA": "3.53",
        "IP": "140.1",
        "Hits": "133",
        "Runs": "55",
        "ER": "55",
        "HR": "18",
        "BB": "37",
        "SO": "116",
        "WHIP": "1.21",
        "Chase%": "31.1",
        "Whiff%": "24.7",
        "GB%": "44.7",
        "FB%": "25.6",
        "G/F": 1.75,
        "Pitch_Zone%": [
            "78",
            "74",
            "43",
            "152",
            "174",
            "97",
            "146",
            "174",
            "122",
            "212",
            "97",
            "374",
            "409"
        ]
    },
    {
        "Player": "Michael Kopech",
        "ID": "656629",
        "Year": 2024,
        "Team": "CWS",
        "Division": "National League West",
        "Type": "Pitcher",
        "Wins": "2",
        "Losses": "8",
        "ERA": "4.74",
        "IP": "43.2",
        "Hits": "35",
        "Runs": "24",
        "ER": "23",
        "HR": "8",
        "BB": "24",
        "SO": "59",
        "WHIP": "1.35",
        "Chase%": "28.8",
        "Whiff%": "32.8",
        "GB%": "38.8",
        "FB%": "38.2",
        "G/F": 1.02,
        "Pitch_Zone%": [
            "103",
            "86",
            "49",
            "53",
            "94",
            "74",
            "24",
            "46",
            "52",
            "251",
            "105",
            "36",
            "170"
        ]
    },
    {
        "Player": "Michael Kopech",
        "ID": "656629",
        "Year": 2024,
        "Team": "LAD",
        "Division": "National League West",
        "Type": "Pitcher",
        "Wins": "4",
        "Losses": "0",
        "ERA": "1.13",
        "IP": "24.0",
        "Hits": "9",
        "Runs": "3",
        "ER": "3",
        "HR": "1",
        "BB": "10",
        "SO": "29",
        "WHIP": "0.79",
        "Chase%": "28.8",
        "Whiff%": "32.8",
        "GB%": "38.8",
        "FB%": "38.2",
        "G/F": 1.02,
        "Pitch_Zone%": [
            "103",
            "86",
            "49",
            "53",
            "94",
            "74",
            "24",
            "46",
            "52",
            "251",
            "105",
            "36",
            "170"
        ]
    },
    {
        "Player": "Michael Kopech",
        "ID": "656629",
        "Year": 2024,
        "Team": "2 Teams",
        "Division": "National League West",
        "Type": "Pitcher",
        "Wins": "6",
        "Losses": "8",
        "ERA": "3.46",
        "IP": "67.2",
        "Hits": "44",
        "Runs": "27",
        "ER": "26",
        "HR": "9",
        "BB": "34",
        "SO": "88",
        "WHIP": "1.15",
        "Chase%": "28.8",
        "Whiff%": "32.8",
        "GB%": "38.8",
        "FB%": "38.2",
        "G/F": 1.02,
        "Pitch_Zone%": [
            "103",
            "86",
            "49",
            "53",
            "94",
            "74",
            "24",
            "46",
            "52",
            "251",
            "105",
            "36",
            "170"
        ]
    },
    {
        "Player": "Tyler Glasnow",
        "ID": "607192",
        "Year": 2024,
        "Team": "LAD",
        "Division": "National League West",
        "Type": "Pitcher",
        "Wins": "9",
        "Losses": "6",
        "ERA": "3.49",
        "IP": "134.0",
        "Hits": "92",
        "Runs": "53",
        "ER": "52",
        "HR": "15",
        "BB": "35",
        "SO": "168",
        "WHIP": "0.95",
        "Chase%": "27.3",
        "Whiff%": "30.9",
        "GB%": "48.3",
        "FB%": "23.7",
        "G/F": 2.04,
        "Pitch_Zone%": [
            "88",
            "151",
            "93",
            "96",
            "168",
            "146",
            "43",
            "133",
            "161",
            "182",
            "156",
            "90",
            "504"
        ]
    }
]